bom/__init__.py
bom/admin.py
bom/apps.py
bom/auth_backends.py
bom/base_classes.py
bom/constants.py
bom/context_processors.py
bom/csv_headers.py
bom/decorators.py
bom/form_fields.py
bom/forms.py
bom/helpers.py
bom/local_settings.py
bom/models.py
bom/part_bom.py
bom/settings.py
bom/tests.py
bom/urls.py
bom/utils.py
bom/validators.py
bom/wsgi.py
bom/migrations/0001_initial.py
bom/migrations/0002_auto_20180908_2151.py
bom/migrations/0003_sellerpart_data_source.py
bom/migrations/0004_auto_20180911_0011.py
bom/migrations/0005_auto_20181007_1934.py
bom/migrations/0006_auto_20181007_1949.py
bom/migrations/0007_auto_20181009_0256.py
bom/migrations/0008_auto_20181030_0427.py
bom/migrations/0009_subpart_reference.py
bom/migrations/0010_auto_20181202_0733.py
bom/migrations/0011_auto_20181202_2113.py
bom/migrations/0012_partchangehistory.py
bom/migrations/0013_auto_20190222_1631.py
bom/migrations/0014_auto_20190223_2353.py
bom/migrations/0015_auto_20190303_1915.py
bom/migrations/0016_auto_20190405_2308.py
bom/migrations/0017_auto_20190616_1912.py
bom/migrations/0018_auto_20190616_2143.py
bom/migrations/0019_auto_20190624_1246.py
bom/migrations/0020_auto_20190627_0207.py
bom/migrations/0021_auto_20190627_0428.py
bom/migrations/0022_auto_20190811_2140.py
bom/migrations/0023_auto_20191205_2351.py
bom/migrations/0024_auto_20191214_1342.py
bom/migrations/0025_auto_20191221_1907.py
bom/migrations/0026_auto_20191222_2258.py
bom/migrations/0027_auto_20191222_2347.py
bom/migrations/0028_partrevision_displayable_synopsis.py
bom/migrations/0029_auto_20191231_1630.py
bom/migrations/0030_auto_20200101_2253.py
bom/migrations/0031_auto_20200104_1352.py
bom/migrations/0032_auto_20200126_1806.py
bom/migrations/0033_auto_20200203_0618.py
bom/migrations/0034_auto_20200222_0359.py
bom/migrations/0035_auto_20200303_0111.py
bom/migrations/0036_auto_20200303_0538.py
bom/migrations/0037_auto_20200405_1642.py
bom/migrations/0038_auto_20200422_0504.py
bom/migrations/0039_auto_20200929_2315.py
django_bom-1.267.dist-info/licenses/LICENSE
django_bom-1.267.dist-info/METADATA
django_bom-1.267.dist-info/WHEEL
django_bom-1.267.dist-info/top_level.txt
django_bom-1.267.dist-info/RECORD
