Metadata-Version: 2.4
Name: django-bom
Version: 1.267
Summary: A simple Django app to manage a bill of materials.
Author-email: Mike Kasparian <mpkasp@gmail.com>
License: GPL-3.0-only
Project-URL: Homepage, https://www.indabom.com/
Classifier: Environment :: Web Environment
Classifier: Framework :: Django
Classifier: Framework :: Django :: 6
Classifier: Intended Audience :: Developers
Classifier: License :: OSI Approved :: GNU General Public License v3 (GPLv3)
Classifier: Operating System :: OS Independent
Classifier: Programming Language :: Python
Classifier: Programming Language :: Python :: 3
Classifier: Programming Language :: Python :: 3.10
Classifier: Programming Language :: Python :: 3.11
Classifier: Programming Language :: Python :: 3.12
Classifier: Programming Language :: Python :: 3 :: Only
Classifier: Topic :: Internet :: WWW/HTTP
Classifier: Topic :: Internet :: WWW/HTTP :: Dynamic Content
Requires-Python: >=3.10
License-File: LICENSE
Requires-Dist: Django>=5.2
Requires-Dist: social-auth-app-django<6,>=5
Requires-Dist: social-auth-core<6,>=4
Requires-Dist: google-api-python-client>=2
Requires-Dist: django-materializecss-form
Requires-Dist: django-money<5,>=3
Dynamic: license-file
